{"header":{"numFound":1,"maxScore":1.0,"queryTime":9,"page":1,"pageSize":10},"results":[{"legalShortName":"Viaa","legalName":"Viaa Christian University of Applied Sciences","websiteUrl":"https://www.viaa.nl/en/","alternativeNames":["Hogeschool Viaa","Viaa Christian University of Applied Sciences","Viaa"],"country":{"code":"NL","label":"Netherlands"},"id":"openorgs____::10b852af099e61b41490b7ab3d1cd34a","pids":[{"scheme":"wikidata","value":"Q2860268"},{"scheme":"ROR","value":"https://ror.org/02ar29j81"},{"scheme":"OrgReg","value":"NL0031"},{"scheme":"ISNI","value":"000000040379503X"},{"scheme":"GRID","value":"grid.466087.b"},{"scheme":"Wikidata","value":"Q2860268"}],"originalIds":["openorgs____::0000055925"]}]}