{"number_of_results": 1804, "time_taken": 5, "items": [{"admin": {"created": {"date": "2018-11-14", "schema_version": "1.0"}, "last_modified": {"date": "2024-12-11", "schema_version": "2.1"}}, "domains": [], "established": 2007, "external_ids": [{"all": ["grid.458380.2"], "preferred": "grid.458380.2", "type": "grid"}, {"all": ["0000 0004 0368 8664"], "preferred": null, "type": "isni"}, {"all": ["Q30259586"], "preferred": null, "type": "wikidata"}], "id": "https://ror.org/05kgbsy64", "links": [{"type": "website", "value": "https://www.spinozacentre.nl/"}], "locations": [{"geonames_details": {"continent_code": "EU", "continent_name": "Europe", "country_code": "NL", "country_name": "The Netherlands", "country_subdivision_code": "NH", "country_subdivision_name": "North Holland", "lat": 52.37403, "lng": 4.88969, "name": "Amsterdam"}, "geonames_id": 2759794}], "names": [{"lang": "en", "types": ["ror_display", "label"], "value": "Spinoza Centre for Neuroimaging"}], "relationships": [{"label": "Netherlands Institute for Neuroscience", "type": "related", "id": "https://ror.org/05csn2x06"}, {"label": "University of Amsterdam", "type": "related", "id": "https://ror.org/04dkp9463"}, {"label": "Vrije Universiteit Amsterdam", "type": "related", "id": "https://ror.org/008xxew50"}], "status": "active", "types": ["other"]}, {"admin": {"created": {"date": "2018-11-14", "schema_version": "1.0"}, "last_modified": {"date": "2024-12-11", "schema_version": "2.1"}}, "domains": [], "established": 1904, "external_ids": [{"all": ["grid.426578.a"], "preferred": "grid.426578.a", "type": "grid"}, {"all": ["0000 0004 1785 0810"], "preferred": null, "type": "isni"}, {"all": ["Q1954331"], "preferred": null, "type": "wikidata"}], "id": "https://ror.org/03scjwb12", "links": [{"type": "website", "value": "https://oneplanet.nl"}, {"type": "wikipedia", "value": "https://en.wikipedia.org/wiki/Museon"}], "locations": [{"geonames_details": {"continent_code": "EU", "continent_name": "Europe", "country_code": "NL", "country_name": "The Netherlands", "country_subdivision_code": "ZH", "country_subdivision_name": "South Holland", "lat": 52.07667, "lng": 4.29861, "name": "The Hague"}, "geonames_id": 2747373}], "names": [{"lang": "nl", "types": ["ror_display", "label"], "value": "Museon-Omniversum"}], "relationships": [], "status": "active", "types": ["archive"]}, {"admin": {"created": {"date": "2022-06-16", "schema_version": "1.0"}, "last_modified": {"date": "2024-12-11", "schema_version": "2.1"}}, "domains": [], "established": 2018, "external_ids": [], "id": "https://ror.org/056j50v04", "links": [{"type": "website", "value": "https://www.gofair.foundation"}], "locations": [{"geonames_details": {"continent_code": "EU", "continent_name": "Europe", "country_code": "NL", "country_name": "The Netherlands", "country_subdivision_code": "ZH", "country_subdivision_name": "South Holland", "lat": 52.15833, "lng": 4.49306, "name": "Leiden"}, "geonames_id": 2751773}], "names": [{"lang": null, "types": ["acronym"], "value": "GFF"}, {"lang": "en", "types": ["ror_display", "label"], "value": "GO FAIR Foundation"}, {"lang": "nl", "types": ["label"], "value": "Stichting GO FAIR"}], "relationships": [], "status": "active", "types": ["nonprofit"]}, {"admin": {"created": {"date": "2018-11-14", "schema_version": "1.0"}, "last_modified": {"date": "2024-12-11", "schema_version": "2.1"}}, "domains": [], "established": 1955, "external_ids": [{"all": ["grid.7861.8"], "preferred": "grid.7861.8", "type": "grid"}, {"all": ["0000 0001 0788 9840"], "preferred": null, "type": "isni"}, {"all": ["Q1341584"], "preferred": null, "type": "wikidata"}], "id": "https://ror.org/04xa4c474", "links": [{"type": "website", "value": "https://www.ecn.nl/"}, {"type": "wikipedia", "value": "http://en.wikipedia.org/wiki/Energy_Research_Centre_of_the_Netherlands"}], "locations": [{"geonames_details": {"continent_code": "EU", "continent_name": "Europe", "country_code": "NL", "country_name": "The Netherlands", "country_subdivision_code": "NH", "country_subdivision_name": "North Holland", "lat": 52.76667, "lng": 4.66111, "name": "Petten"}, "geonames_id": 2748631}], "names": [{"lang": null, "types": ["acronym"], "value": "ECN"}, {"lang": "en", "types": ["ror_display", "label"], "value": "Energy Research Centre of the Netherlands"}], "relationships": [], "status": "active", "types": ["facility"]}, {"admin": {"created": {"date": "2022-08-31", "schema_version": "1.0"}, "last_modified": {"date": "2024-12-11", "schema_version": "2.1"}}, "domains": [], "established": 1633, "external_ids": [{"all": ["0000 0001 1013 9063"], "preferred": "0000 0001 1013 9063", "type": "isni"}, {"all": ["Q186244"], "preferred": "Q186244", "type": "wikidata"}], "id": "https://ror.org/03es66g06", "links": [{"type": "website", "value": "https://www.universiteitleiden.nl/en/science/astronomy"}, {"type": "wikipedia", "value": "https://en.wikipedia.org/wiki/Leiden_Observatory"}], "locations": [{"geonames_details": {"continent_code": "EU", "continent_name": "Europe", "country_code": "NL", "country_name": "The Netherlands", "country_subdivision_code": "ZH", "country_subdivision_name": "South Holland", "lat": 52.15833, "lng": 4.49306, "name": "Leiden"}, "geonames_id": 2751773}], "names": [{"lang": "en", "types": ["ror_display", "label"], "value": "Leiden Observatory"}, {"lang": "nl", "types": ["label"], "value": "Sterrewacht Leiden"}], "relationships": [{"label": "Leiden University", "type": "parent", "id": "https://ror.org/027bh9e22"}], "status": "active", "types": ["facility"]}, {"admin": {"created": {"date": "2018-11-14", "schema_version": "1.0"}, "last_modified": {"date": "2024-12-11", "schema_version": "2.1"}}, "domains": [], "established": 1995, "external_ids": [{"all": ["501100013120"], "preferred": "501100013120", "type": "fundref"}, {"all": ["grid.452397.e"], "preferred": "grid.452397.e", "type": "grid"}, {"all": ["Q130146"], "preferred": null, "type": "wikidata"}], "id": "https://ror.org/01z0wsw92", "links": [{"type": "website", "value": "http://www.ema.europa.eu/ema/"}, {"type": "wikipedia", "value": "https://en.wikipedia.org/wiki/European_Medicines_Agency"}], "locations": [{"geonames_details": {"continent_code": "EU", "continent_name": "Europe", "country_code": "NL", "country_name": "The Netherlands", "country_subdivision_code": "NH", "country_subdivision_name": "North Holland", "lat": 52.37403, "lng": 4.88969, "name": "Amsterdam"}, "geonames_id": 2759794}], "names": [{"lang": null, "types": ["acronym"], "value": "EMA"}, {"lang": "en", "types": ["ror_display", "label"], "value": "European Medicines Agency"}], "relationships": [{"label": "European Union", "type": "parent", "id": "https://ror.org/019w4f821"}], "status": "active", "types": ["funder", "government"]}, {"admin": {"created": {"date": "2019-02-17", "schema_version": "1.0"}, "last_modified": {"date": "2024-12-11", "schema_version": "2.1"}}, "domains": [], "established": 1987, "external_ids": [{"all": ["501100007871"], "preferred": "501100007871", "type": "fundref"}, {"all": ["grid.502795.c"], "preferred": "grid.502795.c", "type": "grid"}, {"all": ["0000 0004 6008 4146"], "preferred": null, "type": "isni"}, {"all": ["Q17153831"], "preferred": null, "type": "wikidata"}], "id": "https://ror.org/05btws897", "links": [{"type": "website", "value": "https://www.ecnp.eu/"}, {"type": "wikipedia", "value": "https://en.wikipedia.org/wiki/European_College_of_Neuropsychopharmacology"}], "locations": [{"geonames_details": {"continent_code": "EU", "continent_name": "Europe", "country_code": "NL", "country_name": "The Netherlands", "country_subdivision_code": "UT", "country_subdivision_name": "Utrecht", "lat": 52.09083, "lng": 5.12222, "name": "Utrecht"}, "geonames_id": 2745912}], "names": [{"lang": null, "types": ["acronym"], "value": "ECNP"}, {"lang": "en", "types": ["ror_display", "label"], "value": "European College of Neuropsychopharmacology"}], "relationships": [], "status": "active", "types": ["funder", "nonprofit"]}, {"admin": {"created": {"date": "2018-11-14", "schema_version": "1.0"}, "last_modified": {"date": "2024-12-11", "schema_version": "2.1"}}, "domains": [], "established": 1861, "external_ids": [{"all": ["501100011069"], "preferred": "501100011069", "type": "fundref"}, {"all": ["grid.491343.8"], "preferred": "grid.491343.8", "type": "grid"}, {"all": ["0000 0004 0621 3912"], "preferred": null, "type": "isni"}], "id": "https://ror.org/02nt7ap43", "links": [{"type": "website", "value": "https://www.verloskunde-academie.nl/"}], "locations": [{"geonames_details": {"continent_code": "EU", "continent_name": "Europe", "country_code": "NL", "country_name": "The Netherlands", "country_subdivision_code": "NH", "country_subdivision_name": "North Holland", "lat": 52.37403, "lng": 4.88969, "name": "Amsterdam"}, "geonames_id": 2759794}], "names": [{"lang": null, "types": ["acronym"], "value": "AVAG"}, {"lang": "nl", "types": ["ror_display", "label"], "value": "Academie Verloskunde Amsterdam Groningen"}], "relationships": [], "status": "active", "types": ["education", "funder"]}, {"admin": {"created": {"date": "2018-11-14", "schema_version": "1.0"}, "last_modified": {"date": "2024-12-11", "schema_version": "2.1"}}, "domains": [], "established": null, "external_ids": [{"all": ["grid.489551.4"], "preferred": "grid.489551.4", "type": "grid"}, {"all": ["0000 0001 1781 3751"], "preferred": null, "type": "isni"}], "id": "https://ror.org/05qaf7a32", "links": [{"type": "website", "value": "http://www.nvog.nl"}], "locations": [{"geonames_details": {"continent_code": "EU", "continent_name": "Europe", "country_code": "NL", "country_name": "The Netherlands", "country_subdivision_code": "UT", "country_subdivision_name": "Utrecht", "lat": 52.09083, "lng": 5.12222, "name": "Utrecht"}, "geonames_id": 2745912}], "names": [{"lang": "en", "types": ["label"], "value": "Dutch Society for Obstetrics and Gynecology"}, {"lang": null, "types": ["acronym"], "value": "NVOG"}, {"lang": "nl", "types": ["ror_display", "label"], "value": "Nederlandse Vereniging voor Obstetrie en Gynaecologie"}], "relationships": [], "status": "active", "types": ["other"]}, {"admin": {"created": {"date": "2018-11-14", "schema_version": "1.0"}, "last_modified": {"date": "2024-12-11", "schema_version": "2.1"}}, "domains": [], "established": null, "external_ids": [{"all": ["grid.489560.6"], "preferred": "grid.489560.6", "type": "grid"}], "id": "https://ror.org/01aq0vw42", "links": [{"type": "website", "value": "https://ergotherapie.nl/"}], "locations": [{"geonames_details": {"continent_code": "EU", "continent_name": "Europe", "country_code": "NL", "country_name": "The Netherlands", "country_subdivision_code": "UT", "country_subdivision_name": "Utrecht", "lat": 52.09083, "lng": 5.12222, "name": "Utrecht"}, "geonames_id": 2745912}], "names": [{"lang": "nl", "types": ["ror_display", "label"], "value": "Ergotherapie Nederland"}, {"lang": "nl", "types": ["label"], "value": "Nederlandse Vereniging van Ergotherapie"}], "relationships": [], "status": "active", "types": ["healthcare"]}, {"admin": {"created": {"date": "2018-11-14", "schema_version": "1.0"}, "last_modified": {"date": "2024-12-11", "schema_version": "2.1"}}, "domains": [], "established": 1931, "external_ids": [{"all": ["grid.489640.7"], "preferred": "grid.489640.7", "type": "grid"}, {"all": ["0000 0001 2215 4121"], "preferred": null, "type": "isni"}], "id": "https://ror.org/03sk8zw22", "links": [{"type": "website", "value": "https://www.internisten.nl/"}], "locations": [{"geonames_details": {"continent_code": "EU", "continent_name": "Europe", "country_code": "NL", "country_name": "The Netherlands", "country_subdivision_code": "UT", "country_subdivision_name": "Utrecht", "lat": 52.09083, "lng": 5.12222, "name": "Utrecht"}, "geonames_id": 2745912}], "names": [{"lang": null, "types": ["acronym"], "value": "NIV"}, {"lang": "nl", "types": ["ror_display", "label"], "value": "Nederlandse Internisten Vereniging"}], "relationships": [], "status": "active", "types": ["nonprofit"]}, {"admin": {"created": {"date": "2018-11-14", "schema_version": "1.0"}, "last_modified": {"date": "2024-12-11", "schema_version": "2.1"}}, "domains": [], "established": 1901, "external_ids": [{"all": ["grid.489662.7"], "preferred": "grid.489662.7", "type": "grid"}, {"all": ["0000 0001 1090 6824"], "preferred": null, "type": "isni"}], "id": "https://ror.org/0480n9h26", "links": [{"type": "website", "value": "https://www.radiologen.nl/"}], "locations": [{"geonames_details": {"continent_code": "EU", "continent_name": "Europe", "country_code": "NL", "country_name": "The Netherlands", "country_subdivision_code": "NB", "country_subdivision_name": "North Brabant", "lat": 51.65333, "lng": 5.2875, "name": "Vught"}, "geonames_id": 2745154}], "names": [{"lang": null, "types": ["acronym"], "value": "NVvR"}, {"lang": "nl", "types": ["ror_display", "label"], "value": "Nederlandse Vereniging voor Radiologie"}], "relationships": [], "status": "active", "types": ["nonprofit"]}, {"admin": {"created": {"date": "2018-11-14", "schema_version": "1.0"}, "last_modified": {"date": "2024-12-11", "schema_version": "2.1"}}, "domains": [], "established": 2004, "external_ids": [{"all": ["grid.489920.e"], "preferred": "grid.489920.e", "type": "grid"}, {"all": ["0000 0004 5938 4758"], "preferred": null, "type": "isni"}], "id": "https://ror.org/03gsbap19", "links": [{"type": "website", "value": "http://www.ctcm.nl/"}], "locations": [{"geonames_details": {"continent_code": "EU", "continent_name": "Europe", "country_code": "NL", "country_name": "The Netherlands", "country_subdivision_code": "LI", "country_subdivision_name": "Limburg", "lat": 50.84833, "lng": 5.68889, "name": "Maastricht"}, "geonames_id": 2751283}], "names": [{"lang": null, "types": ["acronym"], "value": "CTCM"}, {"lang": "en", "types": ["ror_display", "label"], "value": "Clinical Trial Center Maastricht"}], "relationships": [], "status": "active", "types": ["healthcare"]}, {"admin": {"created": {"date": "2018-11-14", "schema_version": "1.0"}, "last_modified": {"date": "2024-12-11", "schema_version": "2.1"}}, "domains": [], "established": 1987, "external_ids": [{"all": ["grid.489978.3"], "preferred": "grid.489978.3", "type": "grid"}, {"all": ["0000 0004 4700 0286"], "preferred": null, "type": "isni"}], "id": "https://ror.org/00m7jsz42", "links": [{"type": "website", "value": "http://www.esho.info"}, {"type": "wikipedia", "value": "https://en.wikipedia.org/wiki/European_Society_for_Hyperthermic_Oncology"}], "locations": [{"geonames_details": {"continent_code": "EU", "continent_name": "Europe", "country_code": "NL", "country_name": "The Netherlands", "country_subdivision_code": "ZH", "country_subdivision_name": "South Holland", "lat": 51.9225, "lng": 4.47917, "name": "Rotterdam"}, "geonames_id": 2747891}], "names": [{"lang": null, "types": ["acronym"], "value": "ESHO"}, {"lang": "en", "types": ["ror_display", "label"], "value": "European Society for Hyperthermic Oncology"}], "relationships": [], "status": "active", "types": ["other"]}, {"admin": {"created": {"date": "2018-11-14", "schema_version": "1.0"}, "last_modified": {"date": "2024-12-11", "schema_version": "2.1"}}, "domains": [], "established": 1968, "external_ids": [{"all": ["grid.490071.b"], "preferred": "grid.490071.b", "type": "grid"}, {"all": ["0000 0004 0499 2158"], "preferred": null, "type": "isni"}], "id": "https://ror.org/01qsyak13", "links": [{"type": "website", "value": "https://www.dianet.nl/"}], "locations": [{"geonames_details": {"continent_code": "EU", "continent_name": "Europe", "country_code": "NL", "country_name": "The Netherlands", "country_subdivision_code": "UT", "country_subdivision_name": "Utrecht", "lat": 52.09083, "lng": 5.12222, "name": "Utrecht"}, "geonames_id": 2745912}], "names": [{"lang": "nl", "types": ["ror_display", "label"], "value": "Dianet"}, {"lang": "nl", "types": ["alias"], "value": "Dianet Thuis in dialysezorg"}], "relationships": [], "status": "active", "types": ["facility"]}, {"admin": {"created": {"date": "2018-11-14", "schema_version": "1.0"}, "last_modified": {"date": "2024-12-11", "schema_version": "2.1"}}, "domains": [], "established": 2010, "external_ids": [{"all": ["grid.490413.b"], "preferred": "grid.490413.b", "type": "grid"}], "id": "https://ror.org/04cm10r73", "links": [{"type": "website", "value": "https://www.sanquin.org/research/ctr-studies/van-rood-center"}], "locations": [{"geonames_details": {"continent_code": "EU", "continent_name": "Europe", "country_code": "NL", "country_name": "The Netherlands", "country_subdivision_code": "ZH", "country_subdivision_name": "South Holland", "lat": 52.15833, "lng": 4.49306, "name": "Leiden"}, "geonames_id": 2751773}], "names": [{"lang": "en", "types": ["ror_display", "label"], "value": "Jon J van Rood Centre for Clinical Transfusion Research"}], "relationships": [{"label": "Leiden University Medical Center", "type": "parent", "id": "https://ror.org/05xvt9f17"}, {"label": "Sanquin", "type": "parent", "id": "https://ror.org/01fm2fv39"}], "status": "active", "types": ["other"]}, {"admin": {"created": {"date": "2018-11-14", "schema_version": "1.0"}, "last_modified": {"date": "2024-12-11", "schema_version": "2.1"}}, "domains": [], "established": 2007, "external_ids": [{"all": ["grid.490748.6"], "preferred": "grid.490748.6", "type": "grid"}], "id": "https://ror.org/002jbbs61", "links": [{"type": "website", "value": "http://continentie-stichting.nl/"}], "locations": [{"geonames_details": {"continent_code": "EU", "continent_name": "Europe", "country_code": "NL", "country_name": "The Netherlands", "country_subdivision_code": "NH", "country_subdivision_name": "North Holland", "lat": 52.34992, "lng": 4.62301, "name": "Heemstede"}, "geonames_id": 2754692}], "names": [{"lang": "nl", "types": ["ror_display", "label"], "value": "Continentie Stichting Nederland"}], "relationships": [], "status": "active", "types": ["other"]}, {"admin": {"created": {"date": "2018-11-14", "schema_version": "1.0"}, "last_modified": {"date": "2024-12-11", "schema_version": "2.1"}}, "domains": [], "established": 1996, "external_ids": [{"all": ["grid.490877.5"], "preferred": "grid.490877.5", "type": "grid"}], "id": "https://ror.org/022p9j404", "links": [{"type": "website", "value": "https://stichting-nice.nl/"}], "locations": [{"geonames_details": {"continent_code": "EU", "continent_name": "Europe", "country_code": "NL", "country_name": "The Netherlands", "country_subdivision_code": "UT", "country_subdivision_name": "Utrecht", "lat": 52.09083, "lng": 5.12222, "name": "Utrecht"}, "geonames_id": 2745912}], "names": [{"lang": null, "types": ["acronym"], "value": "NICE"}, {"lang": "nl", "types": ["ror_display", "label"], "value": "Nationale Intensive Care Evaluatie Stichting"}], "relationships": [], "status": "active", "types": ["nonprofit"]}, {"admin": {"created": {"date": "2018-11-14", "schema_version": "1.0"}, "last_modified": {"date": "2024-12-11", "schema_version": "2.1"}}, "domains": [], "established": 1989, "external_ids": [{"all": ["grid.490896.a"], "preferred": "grid.490896.a", "type": "grid"}], "id": "https://ror.org/05cfhyk75", "links": [{"type": "website", "value": "http://www.neys-vanhoogstraten.nl/"}], "locations": [{"geonames_details": {"continent_code": "EU", "continent_name": "Europe", "country_code": "NL", "country_name": "The Netherlands", "country_subdivision_code": "ZH", "country_subdivision_name": "South Holland", "lat": 52.07667, "lng": 4.29861, "name": "The Hague"}, "geonames_id": 2747373}], "names": [{"lang": "en", "types": ["ror_display", "label"], "value": "Neys-van Hoogstraten Foundation"}], "relationships": [], "status": "active", "types": ["nonprofit"]}, {"admin": {"created": {"date": "2018-11-14", "schema_version": "1.0"}, "last_modified": {"date": "2024-12-11", "schema_version": "2.1"}}, "domains": [], "established": 1980, "external_ids": [{"all": ["grid.491030.f"], "preferred": "grid.491030.f", "type": "grid"}], "id": "https://ror.org/04tagby45", "links": [{"type": "website", "value": "https://www.triodos.nl/nl"}], "locations": [{"geonames_details": {"continent_code": "EU", "continent_name": "Europe", "country_code": "NL", "country_name": "The Netherlands", "country_subdivision_code": "UT", "country_subdivision_name": "Utrecht", "lat": 52.09, "lng": 5.23333, "name": "Zeist"}, "geonames_id": 2743977}], "names": [{"lang": "en", "types": ["ror_display", "label"], "value": "Triodos Bank"}], "relationships": [], "status": "active", "types": ["other"]}], "meta": {"types": [{"id": "company", "title": "company", "count": 589}, {"id": "other", "title": "other", "count": 312}, {"id": "nonprofit", "title": "nonprofit", "count": 284}, {"id": "funder", "title": "funder", "count": 267}, {"id": "healthcare", "title": "healthcare", "count": 245}, {"id": "education", "title": "education", "count": 131}, {"id": "facility", "title": "facility", "count": 126}, {"id": "government", "title": "government", "count": 77}, {"id": "archive", "title": "archive", "count": 39}], "countries": [{"id": "nl", "title": "Netherlands", "count": 1804}], "continents": [{"id": "eu", "title": "Europe", "count": 1804}], "statuses": [{"id": "active", "title": "active", "count": 1804}]}}