{"number_of_results": 1804, "time_taken": 11, "items": [{"admin": {"created": {"date": "2018-11-14", "schema_version": "1.0"}, "last_modified": {"date": "2024-12-11", "schema_version": "2.1"}}, "domains": [], "established": 1985, "external_ids": [{"all": ["grid.424239.a"], "preferred": "grid.424239.a", "type": "grid"}, {"all": ["Q30284776"], "preferred": null, "type": "wikidata"}], "id": "https://ror.org/01fr3an09", "links": [{"type": "website", "value": "https://www.bmt.org/"}, {"type": "wikipedia", "value": "https://en.wikipedia.org/wiki/BMT_Group"}], "locations": [{"geonames_details": {"continent_code": "EU", "continent_name": "Europe", "country_code": "NL", "country_name": "The Netherlands", "country_subdivision_code": "NH", "country_subdivision_name": "North Holland", "lat": 52.37403, "lng": 4.88969, "name": "Amsterdam"}, "geonames_id": 2759794}], "names": [{"lang": null, "types": ["ror_display", "label"], "value": "BMT Group (Netherlands)"}, {"lang": null, "types": ["alias"], "value": "British Maritime Technology"}], "relationships": [{"label": "BMT Group (United Kingdom)", "type": "parent", "id": "https://ror.org/02npppw10"}], "status": "active", "types": ["company"]}, {"admin": {"created": {"date": "2018-11-14", "schema_version": "1.0"}, "last_modified": {"date": "2024-12-11", "schema_version": "2.1"}}, "domains": [], "established": 2010, "external_ids": [{"all": ["grid.424362.5"], "preferred": "grid.424362.5", "type": "grid"}, {"all": ["Q30254411"], "preferred": null, "type": "wikidata"}], "id": "https://ror.org/050teng13", "links": [{"type": "website", "value": "https://www.humaneticsatd.com/"}], "locations": [{"geonames_details": {"continent_code": "EU", "continent_name": "Europe", "country_code": "NL", "country_name": "The Netherlands", "country_subdivision_code": "ZH", "country_subdivision_name": "South Holland", "lat": 52.07667, "lng": 4.29861, "name": "The Hague"}, "geonames_id": 2747373}], "names": [{"lang": null, "types": ["ror_display", "label"], "value": "Humanetics Innovative Solutions (Netherlands)"}], "relationships": [], "status": "active", "types": ["company"]}, {"admin": {"created": {"date": "2018-11-14", "schema_version": "1.0"}, "last_modified": {"date": "2024-12-11", "schema_version": "2.1"}}, "domains": [], "established": 2012, "external_ids": [{"all": ["grid.424378.e"], "preferred": "grid.424378.e", "type": "grid"}, {"all": ["Q30254424"], "preferred": null, "type": "wikidata"}], "id": "https://ror.org/023zgnb96", "links": [{"type": "website", "value": "https://www.dyadic.com/"}], "locations": [{"geonames_details": {"continent_code": "EU", "continent_name": "Europe", "country_code": "NL", "country_name": "The Netherlands", "country_subdivision_code": "GE", "country_subdivision_name": "Gelderland", "lat": 51.97, "lng": 5.66667, "name": "Wageningen"}, "geonames_id": 2745088}], "names": [{"lang": null, "types": ["ror_display", "label"], "value": "Dyadic (Netherlands)"}], "relationships": [], "status": "active", "types": ["company"]}, {"admin": {"created": {"date": "2018-11-14", "schema_version": "1.0"}, "last_modified": {"date": "2024-12-11", "schema_version": "2.1"}}, "domains": [], "established": 1985, "external_ids": [{"all": ["grid.424388.1"], "preferred": "grid.424388.1", "type": "grid"}], "id": "https://ror.org/008wfp513", "links": [{"type": "website", "value": "http://cs.bciglobal.com/"}], "locations": [{"geonames_details": {"continent_code": "EU", "continent_name": "Europe", "country_code": "NL", "country_name": "The Netherlands", "country_subdivision_code": "GE", "country_subdivision_name": "Gelderland", "lat": 51.8425, "lng": 5.85278, "name": "Nijmegen"}, "geonames_id": 2750053}], "names": [{"lang": null, "types": ["acronym"], "value": "BCI"}, {"lang": null, "types": ["ror_display", "label"], "value": "Buck Consultants International"}], "relationships": [], "status": "active", "types": ["company"]}, {"admin": {"created": {"date": "2018-11-14", "schema_version": "1.0"}, "last_modified": {"date": "2024-12-11", "schema_version": "2.1"}}, "domains": [], "established": 1967, "external_ids": [{"all": ["grid.424535.1"], "preferred": "grid.424535.1", "type": "grid"}, {"all": ["0000 0004 0646 5773"], "preferred": null, "type": "isni"}, {"all": ["Q30712705"], "preferred": null, "type": "wikidata"}], "id": "https://ror.org/03amxdk57", "links": [{"type": "website", "value": "https://www.nl.capgemini.com/"}, {"type": "wikipedia", "value": "https://en.wikipedia.org/wiki/Capgemini"}], "locations": [{"geonames_details": {"continent_code": "EU", "continent_name": "Europe", "country_code": "NL", "country_name": "The Netherlands", "country_subdivision_code": "UT", "country_subdivision_name": "Utrecht", "lat": 52.09083, "lng": 5.12222, "name": "Utrecht"}, "geonames_id": 2745912}], "names": [{"lang": null, "types": ["ror_display", "label"], "value": "Capgemini (Netherlands)"}], "relationships": [{"label": "Capgemini (France)", "type": "parent", "id": "https://ror.org/03qx9tc91"}], "status": "active", "types": ["company"]}, {"admin": {"created": {"date": "2018-11-14", "schema_version": "1.0"}, "last_modified": {"date": "2024-12-11", "schema_version": "2.1"}}, "domains": [], "established": 1876, "external_ids": [{"all": ["grid.424643.3"], "preferred": "grid.424643.3", "type": "grid"}, {"all": ["Q29124035"], "preferred": null, "type": "wikidata"}], "id": "https://ror.org/01h4rpv44", "links": [{"type": "website", "value": "https://www.ericsson.com/"}, {"type": "wikipedia", "value": "https://en.wikipedia.org/wiki/Ericsson"}], "locations": [{"geonames_details": {"continent_code": "EU", "continent_name": "Europe", "country_code": "NL", "country_name": "The Netherlands", "country_subdivision_code": "NB", "country_subdivision_name": "North Brabant", "lat": 51.58656, "lng": 4.77596, "name": "Breda"}, "geonames_id": 2758401}], "names": [{"lang": null, "types": ["ror_display", "label"], "value": "Ericsson (Netherlands)"}, {"lang": null, "types": ["alias"], "value": "Telefonaktiebolaget L. M. Ericsson"}], "relationships": [{"label": "Ericsson (Sweden)", "type": "parent", "id": "https://ror.org/05a7rhx54"}], "status": "active", "types": ["company"]}, {"admin": {"created": {"date": "2018-11-14", "schema_version": "1.0"}, "last_modified": {"date": "2024-12-11", "schema_version": "2.1"}}, "domains": [], "established": 1983, "external_ids": [{"all": ["grid.424662.0"], "preferred": "grid.424662.0", "type": "grid"}, {"all": ["Q30254551"], "preferred": null, "type": "wikidata"}], "id": "https://ror.org/03j7xe433", "links": [{"type": "website", "value": "https://www.hauzertechnocoating.com/"}], "locations": [{"geonames_details": {"continent_code": "EU", "continent_name": "Europe", "country_code": "NL", "country_name": "The Netherlands", "country_subdivision_code": "LI", "country_subdivision_name": "Limburg", "lat": 51.37, "lng": 6.16806, "name": "Venlo"}, "geonames_id": 2745641}], "names": [{"lang": null, "types": ["ror_display", "label"], "value": "Hauzer (Netherlands)"}, {"lang": null, "types": ["alias"], "value": "Hauzer Techno Coating"}], "relationships": [], "status": "active", "types": ["company"]}, {"admin": {"created": {"date": "2018-11-14", "schema_version": "1.0"}, "last_modified": {"date": "2024-12-11", "schema_version": "2.1"}}, "domains": [], "established": 1984, "external_ids": [{"all": ["grid.424674.7"], "preferred": "grid.424674.7", "type": "grid"}, {"all": ["Q29653650"], "preferred": null, "type": "wikidata"}], "id": "https://ror.org/055fajc83", "links": [], "locations": [{"geonames_details": {"continent_code": "EU", "continent_name": "Europe", "country_code": "NL", "country_name": "The Netherlands", "country_subdivision_code": "UT", "country_subdivision_name": "Utrecht", "lat": 52.09083, "lng": 5.12222, "name": "Utrecht"}, "geonames_id": 2745912}], "names": [{"lang": null, "types": ["ror_display", "label"], "value": "Frog AGV Systems (Netherlands)"}], "relationships": [], "status": "active", "types": ["company"]}, {"admin": {"created": {"date": "2018-11-14", "schema_version": "1.0"}, "last_modified": {"date": "2024-12-11", "schema_version": "2.1"}}, "domains": [], "established": 1998, "external_ids": [{"all": ["grid.424715.1"], "preferred": "grid.424715.1", "type": "grid"}, {"all": ["Q2219291"], "preferred": null, "type": "wikidata"}], "id": "https://ror.org/01n8cxz90", "links": [], "locations": [{"geonames_details": {"continent_code": "EU", "continent_name": "Europe", "country_code": "NL", "country_name": "The Netherlands", "country_subdivision_code": "GE", "country_subdivision_name": "Gelderland", "lat": 52.21, "lng": 5.96944, "name": "Apeldoorn"}, "geonames_id": 2759706}], "names": [{"lang": null, "types": ["acronym"], "value": "HITT"}, {"lang": null, "types": ["ror_display", "label"], "value": "Holland Institute of Traffic Technology"}], "relationships": [], "status": "active", "types": ["company"]}, {"admin": {"created": {"date": "2018-11-14", "schema_version": "1.0"}, "last_modified": {"date": "2024-12-11", "schema_version": "2.1"}}, "domains": [], "established": 1922, "external_ids": [{"all": ["grid.424717.3"], "preferred": "grid.424717.3", "type": "grid"}, {"all": ["0000 0004 0630 2624"], "preferred": null, "type": "isni"}, {"all": ["Q3913196"], "preferred": null, "type": "wikidata"}], "id": "https://ror.org/032tp7158", "links": [{"type": "website", "value": "https://www.thalesgroup.com/en/countries/europe/netherlands"}, {"type": "wikipedia", "value": "https://en.wikipedia.org/wiki/Thales_Nederland"}], "locations": [{"geonames_details": {"continent_code": "EU", "continent_name": "Europe", "country_code": "NL", "country_name": "The Netherlands", "country_subdivision_code": "OV", "country_subdivision_name": "Overijssel", "lat": 52.26583, "lng": 6.79306, "name": "Hengelo"}, "geonames_id": 2754394}], "names": [{"lang": null, "types": ["alias"], "value": "Hollandse Signaalapparaten B.V."}, {"lang": null, "types": ["alias"], "value": "Signaal"}, {"lang": null, "types": ["ror_display", "label"], "value": "Thales (Netherlands)"}], "relationships": [{"label": "Thales (France)", "type": "parent", "id": "https://ror.org/04emwm605"}], "status": "active", "types": ["company"]}, {"admin": {"created": {"date": "2018-11-14", "schema_version": "1.0"}, "last_modified": {"date": "2024-12-11", "schema_version": "2.1"}}, "domains": [], "established": null, "external_ids": [{"all": ["grid.424751.1"], "preferred": "grid.424751.1", "type": "grid"}, {"all": ["0000 0001 2007 1170"], "preferred": null, "type": "isni"}], "id": "https://ror.org/02mm95a26", "links": [{"type": "website", "value": "http://www.vggm.nl/vggm"}], "locations": [{"geonames_details": {"continent_code": "EU", "continent_name": "Europe", "country_code": "NL", "country_name": "The Netherlands", "country_subdivision_code": "GE", "country_subdivision_name": "Gelderland", "lat": 51.98, "lng": 5.91111, "name": "Arnhem"}, "geonames_id": 2759661}], "names": [{"lang": null, "types": ["acronym"], "value": "VGGM"}, {"lang": "nl", "types": ["ror_display", "label"], "value": "Veiligheids- en Gezondheidsregio Gelderland-Midden"}, {"lang": "nl", "types": ["alias"], "value": "Veiligheidsregio Gelderland Midden"}], "relationships": [], "status": "active", "types": ["government"]}, {"admin": {"created": {"date": "2018-11-14", "schema_version": "1.0"}, "last_modified": {"date": "2024-12-11", "schema_version": "2.1"}}, "domains": [], "established": 2005, "external_ids": [{"all": ["grid.424762.1"], "preferred": "grid.424762.1", "type": "grid"}, {"all": ["Q30254597"], "preferred": null, "type": "wikidata"}], "id": "https://ror.org/02kgzq677", "links": [{"type": "website", "value": "http://www.hybridcatalysis.com/"}], "locations": [{"geonames_details": {"continent_code": "EU", "continent_name": "Europe", "country_code": "NL", "country_name": "The Netherlands", "country_subdivision_code": "NB", "country_subdivision_name": "North Brabant", "lat": 51.44083, "lng": 5.47778, "name": "Eindhoven"}, "geonames_id": 2756253}], "names": [{"lang": null, "types": ["ror_display", "label"], "value": "Hybrid Catalysis (Netherlands)"}], "relationships": [], "status": "active", "types": ["company"]}, {"admin": {"created": {"date": "2018-11-14", "schema_version": "1.0"}, "last_modified": {"date": "2024-12-11", "schema_version": "2.1"}}, "domains": [], "established": 2002, "external_ids": [{"all": ["grid.424775.7"], "preferred": "grid.424775.7", "type": "grid"}], "id": "https://ror.org/05pfyvd35", "links": [{"type": "website", "value": "http://www.hygear.nl/"}], "locations": [{"geonames_details": {"continent_code": "EU", "continent_name": "Europe", "country_code": "NL", "country_name": "The Netherlands", "country_subdivision_code": "GE", "country_subdivision_name": "Gelderland", "lat": 51.98, "lng": 5.91111, "name": "Arnhem"}, "geonames_id": 2759661}], "names": [{"lang": null, "types": ["ror_display", "label"], "value": "HyGear (Netherlands)"}], "relationships": [], "status": "active", "types": ["company"]}, {"admin": {"created": {"date": "2018-11-14", "schema_version": "1.0"}, "last_modified": {"date": "2024-12-11", "schema_version": "2.1"}}, "domains": [], "established": 1993, "external_ids": [{"all": ["grid.424778.a"], "preferred": "grid.424778.a", "type": "grid"}, {"all": ["0000 0001 2181 8723"], "preferred": null, "type": "isni"}, {"all": ["Q550143"], "preferred": null, "type": "wikidata"}], "id": "https://ror.org/0315hq159", "links": [{"type": "website", "value": "http://www.ecnc.org/"}, {"type": "wikipedia", "value": "https://en.wikipedia.org/wiki/European_Centre_for_Nature_Conservation"}], "locations": [{"geonames_details": {"continent_code": "EU", "continent_name": "Europe", "country_code": "NL", "country_name": "The Netherlands", "country_subdivision_code": "NB", "country_subdivision_name": "North Brabant", "lat": 51.55551, "lng": 5.0913, "name": "Tilburg"}, "geonames_id": 2746301}], "names": [{"lang": null, "types": ["acronym"], "value": "ECNC"}, {"lang": "en", "types": ["ror_display", "label"], "value": "European Centre for Nature Conservation"}], "relationships": [], "status": "active", "types": ["nonprofit"]}, {"admin": {"created": {"date": "2018-11-14", "schema_version": "1.0"}, "last_modified": {"date": "2024-12-11", "schema_version": "2.1"}}, "domains": [], "established": 1993, "external_ids": [{"all": ["grid.424818.3"], "preferred": "grid.424818.3", "type": "grid"}, {"all": ["0000 0004 0513 9001"], "preferred": null, "type": "isni"}, {"all": ["Q30254629"], "preferred": null, "type": "wikidata"}], "id": "https://ror.org/059ddw530", "links": [{"type": "website", "value": "http://www.ibspe.com/"}], "locations": [{"geonames_details": {"continent_code": "EU", "continent_name": "Europe", "country_code": "NL", "country_name": "The Netherlands", "country_subdivision_code": "NB", "country_subdivision_name": "North Brabant", "lat": 51.44083, "lng": 5.47778, "name": "Eindhoven"}, "geonames_id": 2756253}], "names": [{"lang": null, "types": ["ror_display", "label"], "value": "IBS Precision Engineering (Netherlands)"}], "relationships": [], "status": "active", "types": ["company"]}, {"admin": {"created": {"date": "2018-11-14", "schema_version": "1.0"}, "last_modified": {"date": "2024-12-11", "schema_version": "2.1"}}, "domains": [], "established": null, "external_ids": [{"all": ["grid.424821.9"], "preferred": "grid.424821.9", "type": "grid"}], "id": "https://ror.org/03s3e7380", "links": [{"type": "website", "value": "http://www.effab.org/"}], "locations": [{"geonames_details": {"continent_code": "EU", "continent_name": "Europe", "country_code": "NL", "country_name": "The Netherlands", "country_subdivision_code": "GE", "country_subdivision_name": "Gelderland", "lat": 51.97, "lng": 5.66667, "name": "Wageningen"}, "geonames_id": 2745088}], "names": [{"lang": null, "types": ["acronym"], "value": "EFFAB"}, {"lang": "en", "types": ["ror_display", "label"], "value": "European Forum of Farm Animal Breeders"}], "relationships": [], "status": "active", "types": ["other"]}, {"admin": {"created": {"date": "2018-11-14", "schema_version": "1.0"}, "last_modified": {"date": "2024-12-11", "schema_version": "2.1"}}, "domains": [], "established": 1991, "external_ids": [{"all": ["grid.424934.c"], "preferred": "grid.424934.c", "type": "grid"}, {"all": ["Q30254692"], "preferred": null, "type": "wikidata"}], "id": "https://ror.org/01c0de609", "links": [{"type": "website", "value": "https://www.imix.nl/"}], "locations": [{"geonames_details": {"continent_code": "EU", "continent_name": "Europe", "country_code": "NL", "country_name": "The Netherlands", "country_subdivision_code": "GE", "country_subdivision_name": "Gelderland", "lat": 52.21, "lng": 5.96944, "name": "Apeldoorn"}, "geonames_id": 2759706}], "names": [{"lang": null, "types": ["ror_display", "label"], "value": "IMIX Vision Support Systems (Netherlands)"}], "relationships": [], "status": "active", "types": ["company"]}, {"admin": {"created": {"date": "2018-11-14", "schema_version": "1.0"}, "last_modified": {"date": "2024-12-11", "schema_version": "2.1"}}, "domains": [], "established": 1981, "external_ids": [{"all": ["grid.424938.0"], "preferred": "grid.424938.0", "type": "grid"}, {"all": ["0000 0004 0624 2983"], "preferred": null, "type": "isni"}], "id": "https://ror.org/003h0ev22", "links": [{"type": "website", "value": "https://www.amsterdam.nl/"}], "locations": [{"geonames_details": {"continent_code": "EU", "continent_name": "Europe", "country_code": "NL", "country_name": "The Netherlands", "country_subdivision_code": "NH", "country_subdivision_name": "North Holland", "lat": 52.37403, "lng": 4.88969, "name": "Amsterdam"}, "geonames_id": 2759794}], "names": [{"lang": "nl", "types": ["ror_display", "label"], "value": "Gemeente Amsterdam"}], "relationships": [], "status": "active", "types": ["government"]}, {"admin": {"created": {"date": "2018-11-14", "schema_version": "1.0"}, "last_modified": {"date": "2024-12-11", "schema_version": "2.1"}}, "domains": [], "established": null, "external_ids": [{"all": ["grid.424941.e"], "preferred": "grid.424941.e", "type": "grid"}], "id": "https://ror.org/04dyx6987", "links": [{"type": "website", "value": "http://www.eindhoven.nl/en.htm"}], "locations": [{"geonames_details": {"continent_code": "EU", "continent_name": "Europe", "country_code": "NL", "country_name": "The Netherlands", "country_subdivision_code": "NB", "country_subdivision_name": "North Brabant", "lat": 51.44083, "lng": 5.47778, "name": "Eindhoven"}, "geonames_id": 2756253}], "names": [{"lang": "nl", "types": ["ror_display", "label"], "value": "Gemeente Eindhoven"}], "relationships": [], "status": "active", "types": ["government"]}, {"admin": {"created": {"date": "2018-11-14", "schema_version": "1.0"}, "last_modified": {"date": "2024-12-11", "schema_version": "2.1"}}, "domains": [], "established": null, "external_ids": [{"all": ["grid.424943.c"], "preferred": "grid.424943.c", "type": "grid"}, {"all": ["0000 0004 0413 9974"], "preferred": null, "type": "isni"}, {"all": ["Q2680952"], "preferred": null, "type": "wikidata"}], "id": "https://ror.org/03ma5tr22", "links": [{"type": "website", "value": "http://www.rotterdam.nl/"}, {"type": "wikipedia", "value": "https://en.wikipedia.org/wiki/Government_of_Rotterdam"}], "locations": [{"geonames_details": {"continent_code": "EU", "continent_name": "Europe", "country_code": "NL", "country_name": "The Netherlands", "country_subdivision_code": "ZH", "country_subdivision_name": "South Holland", "lat": 51.9225, "lng": 4.47917, "name": "Rotterdam"}, "geonames_id": 2747891}], "names": [{"lang": "nl", "types": ["ror_display", "label"], "value": "Gemeente Rotterdam"}], "relationships": [], "status": "active", "types": ["government"]}], "meta": {"types": [{"id": "company", "title": "company", "count": 589}, {"id": "other", "title": "other", "count": 312}, {"id": "nonprofit", "title": "nonprofit", "count": 284}, {"id": "funder", "title": "funder", "count": 267}, {"id": "healthcare", "title": "healthcare", "count": 245}, {"id": "education", "title": "education", "count": 131}, {"id": "facility", "title": "facility", "count": 126}, {"id": "government", "title": "government", "count": 77}, {"id": "archive", "title": "archive", "count": 39}], "countries": [{"id": "nl", "title": "Netherlands", "count": 1804}], "continents": [{"id": "eu", "title": "Europe", "count": 1804}], "statuses": [{"id": "active", "title": "active", "count": 1804}]}}