{"number_of_results": 7, "time_taken": 1, "items": [{"admin": {"created": {"date": "2018-11-14", "schema_version": "1.0"}, "last_modified": {"date": "2024-12-11", "schema_version": "2.1"}}, "domains": [], "established": 1855, "external_ids": [{"all": ["grid.416617.3"], "preferred": "grid.416617.3", "type": "grid"}, {"all": ["0000 0004 0644 3910"], "preferred": null, "type": "isni"}], "id": "https://ror.org/003mpgw14", "links": [{"type": "website", "value": "http://www.sehos.cw/"}], "locations": [{"geonames_details": {"continent_code": "NA", "continent_name": "North America", "country_code": "CW", "country_name": "Cura\u00e7ao", "country_subdivision_code": null, "country_subdivision_name": null, "lat": 12.12246, "lng": -68.88641, "name": "Willemstad"}, "geonames_id": 3513090}], "names": [{"lang": "en", "types": ["ror_display", "label"], "value": "St. Elisabeth Hospital"}], "relationships": [], "status": "active", "types": ["healthcare"]}, {"admin": {"created": {"date": "2018-11-14", "schema_version": "1.0"}, "last_modified": {"date": "2024-12-11", "schema_version": "2.1"}}, "domains": [], "established": null, "external_ids": [{"all": ["grid.452305.5"], "preferred": "grid.452305.5", "type": "grid"}, {"all": ["Q19901643"], "preferred": null, "type": "wikidata"}], "id": "https://ror.org/02fjj1z35", "links": [{"type": "website", "value": "http://www.carmabi.org/"}, {"type": "wikipedia", "value": "https://en.wikipedia.org/wiki/Caribbean_Research_and_Management_of_Biodiversity_Foundation"}], "locations": [{"geonames_details": {"continent_code": "NA", "continent_name": "North America", "country_code": "CW", "country_name": "Cura\u00e7ao", "country_subdivision_code": null, "country_subdivision_name": null, "lat": 12.12246, "lng": -68.88641, "name": "Willemstad"}, "geonames_id": 3513090}], "names": [{"lang": null, "types": ["acronym"], "value": "CARMABI"}, {"lang": "en", "types": ["alias"], "value": "CARMABI Foundation"}, {"lang": "en", "types": ["ror_display", "label"], "value": "Caribbean Research and Management of Biodiversity Foundation"}, {"lang": "en", "types": ["alias"], "value": "The Caribbean Marine Biological Institute"}], "relationships": [], "status": "active", "types": ["education"]}, {"admin": {"created": {"date": "2018-11-14", "schema_version": "1.0"}, "last_modified": {"date": "2024-12-11", "schema_version": "2.1"}}, "domains": [], "established": null, "external_ids": [{"all": ["grid.449410.c"], "preferred": "grid.449410.c", "type": "grid"}, {"all": ["0000 0004 5375 8528"], "preferred": null, "type": "isni"}, {"all": ["Q7590045"], "preferred": null, "type": "wikidata"}], "id": "https://ror.org/04ft1xc20", "links": [{"type": "website", "value": "https://www.martinus.edu/"}, {"type": "wikipedia", "value": "https://en.wikipedia.org/wiki/St._Martinus_University_Faculty_of_Medicine"}], "locations": [{"geonames_details": {"continent_code": "NA", "continent_name": "North America", "country_code": "CW", "country_name": "Cura\u00e7ao", "country_subdivision_code": null, "country_subdivision_name": null, "lat": 12.12246, "lng": -68.88641, "name": "Willemstad"}, "geonames_id": 3513090}], "names": [{"lang": "en", "types": ["ror_display", "label"], "value": "St. Martinus University"}], "relationships": [], "status": "active", "types": ["education"]}, {"admin": {"created": {"date": "2021-09-23", "schema_version": "1.0"}, "last_modified": {"date": "2024-12-11", "schema_version": "2.1"}}, "domains": [], "established": 1998, "external_ids": [{"all": ["grid.511863.8"], "preferred": "grid.511863.8", "type": "grid"}], "id": "https://ror.org/03ybh5p71", "links": [{"type": "website", "value": "https://naam.cw/"}], "locations": [{"geonames_details": {"continent_code": "NA", "continent_name": "North America", "country_code": "CW", "country_name": "Cura\u00e7ao", "country_subdivision_code": null, "country_subdivision_name": null, "lat": 12.12246, "lng": -68.88641, "name": "Willemstad"}, "geonames_id": 3513090}], "names": [{"lang": null, "types": ["acronym"], "value": "NAAM"}, {"lang": "en", "types": ["ror_display", "label"], "value": "National Archeological Anthropological Memory Management"}], "relationships": [], "status": "active", "types": ["nonprofit"]}, {"admin": {"created": {"date": "2018-11-14", "schema_version": "1.0"}, "last_modified": {"date": "2024-12-11", "schema_version": "2.1"}}, "domains": ["uoc.cw"], "established": 1979, "external_ids": [{"all": ["grid.449655.f"], "preferred": "grid.449655.f", "type": "grid"}, {"all": ["0000 0004 0593 2640"], "preferred": null, "type": "isni"}, {"all": ["Q1708838"], "preferred": null, "type": "wikidata"}], "id": "https://ror.org/02a46nr93", "links": [{"type": "website", "value": "https://www.uoc.cw"}, {"type": "wikipedia", "value": "https://en.wikipedia.org/wiki/University_of_Cura%C3%A7ao"}], "locations": [{"geonames_details": {"continent_code": "NA", "continent_name": "North America", "country_code": "CW", "country_name": "Cura\u00e7ao", "country_subdivision_code": null, "country_subdivision_name": null, "lat": 12.12246, "lng": -68.88641, "name": "Willemstad"}, "geonames_id": 3513090}], "names": [{"lang": "en", "types": ["alias"], "value": "Antillean College of Technology"}, {"lang": "en", "types": ["alias"], "value": "College of the Netherlands Antilles"}, {"lang": "nl", "types": ["label"], "value": "Universiteit van Cura\u00e7ao"}, {"lang": null, "types": ["ror_display", "label"], "value": "University of Cura\u00e7ao"}, {"lang": null, "types": ["alias"], "value": "University of Cura\u00e7ao mr. dr. Moises Frumencio da Costa Gomez"}, {"lang": "en", "types": ["alias"], "value": "University of the Netherlands Antilles"}], "relationships": [], "status": "active", "types": ["education"]}, {"admin": {"created": {"date": "2018-11-14", "schema_version": "1.0"}, "last_modified": {"date": "2026-01-29", "schema_version": "2.1"}}, "domains": ["avalonu.org"], "established": 2003, "external_ids": [{"all": ["grid.427640.3"], "preferred": "grid.427640.3", "type": "grid"}, {"all": ["0000 0004 4689 1072"], "preferred": null, "type": "isni"}, {"all": ["Q4827610"], "preferred": null, "type": "wikidata"}], "id": "https://ror.org/03paye555", "links": [{"type": "website", "value": "https://avalonu.org"}, {"type": "wikipedia", "value": "https://en.wikipedia.org/wiki/Avalon_University_School_of_Medicine"}], "locations": [{"geonames_details": {"continent_code": "NA", "continent_name": "North America", "country_code": "CW", "country_name": "Cura\u00e7ao", "country_subdivision_code": null, "country_subdivision_name": null, "lat": 12.12246, "lng": -68.88641, "name": "Willemstad"}, "geonames_id": 3513090}], "names": [{"lang": null, "types": ["acronym"], "value": "AUSOM"}, {"lang": "en", "types": ["ror_display", "label"], "value": "Avalon University School of Medicine"}, {"lang": "en", "types": ["alias"], "value": "Xavier University School of Medicine"}], "relationships": [], "status": "active", "types": ["education"]}, {"admin": {"created": {"date": "2026-02-24", "schema_version": "2.1"}, "last_modified": {"date": "2026-02-24", "schema_version": "2.1"}}, "domains": ["cmc.cw"], "established": 2019, "external_ids": [{"all": ["Q63981880"], "preferred": "Q63981880", "type": "wikidata"}], "id": "https://ror.org/02acpdc95", "links": [{"type": "website", "value": "https://cmc.cw"}, {"type": "wikipedia", "value": "https://en.wikipedia.org/wiki/Cura%C3%A7ao_Medical_Center"}], "locations": [{"geonames_details": {"continent_code": "NA", "continent_name": "North America", "country_code": "CW", "country_name": "Cura\u00e7ao", "country_subdivision_code": null, "country_subdivision_name": null, "lat": 12.12246, "lng": -68.88641, "name": "Willemstad"}, "geonames_id": 3513090}], "names": [{"lang": "en", "types": ["acronym"], "value": "CMC"}, {"lang": "en", "types": ["label", "ror_display"], "value": "Cura\u00e7ao Medical Center"}, {"lang": "en", "types": ["alias"], "value": "SEHOS"}, {"lang": "en", "types": ["alias"], "value": "Sint-Elisabeth Hospital"}], "relationships": [], "status": "active", "types": ["healthcare"]}], "meta": {"types": [{"id": "education", "title": "education", "count": 4}, {"id": "healthcare", "title": "healthcare", "count": 2}, {"id": "nonprofit", "title": "nonprofit", "count": 1}], "countries": [{"id": "cw", "title": "Curacao", "count": 7}], "continents": [{"id": "na", "title": "North America", "count": 7}], "statuses": [{"id": "active", "title": "active", "count": 7}]}}